<annotation>
	<folder>data_images</folder>
	<filename>cat047.jpg</filename>
	<path>C:\Users\wikad\Desktop\yolo_object\Notes\1_datapreparation\data_images\cat047.jpg</path>
	<source>
		<database>Unknown</database>
	</source>
	<size>
		<width>3855</width>
		<height>2500</height>
		<depth>3</depth>
	</size>
	<segmented>0</segmented>
	<object>
		<name>cat</name>
		<pose>Unspecified</pose>
		<truncated>0</truncated>
		<difficult>0</difficult>
		<bndbox>
			<xmin>514</xmin>
			<ymin>404</ymin>
			<xmax>3161</xmax>
			<ymax>1746</ymax>
		</bndbox>
	</object>
</annotation>
